MANIFEST.in
README
setup.py
CodernityDBHTTP/__init__.py
CodernityDBHTTP/all_exceptions.py
CodernityDBHTTP/app.py
CodernityDBHTTP/database_gevent.py
CodernityDBHTTP/database_threads.py
CodernityDBHTTP/misc.py
CodernityDBHTTP/server.py
CodernityDBHTTP/server_gevent.py
CodernityDBHTTP/server_wsgiref.py
CodernityDBHTTP/interface/app.css
CodernityDBHTTP/interface/index.html
CodernityDBHTTP/interface/bootstrap/css/bootstrap-responsive.css
CodernityDBHTTP/interface/bootstrap/css/bootstrap.css
CodernityDBHTTP/interface/bootstrap/img/glyphicons-halflings-white.png
CodernityDBHTTP/interface/bootstrap/img/glyphicons-halflings.png
CodernityDBHTTP/interface/bootstrap/js/bootstrap-alert.js
CodernityDBHTTP/interface/bootstrap/js/bootstrap-dropdown.js
CodernityDBHTTP/interface/bootstrap/js/bootstrap-modal.js
CodernityDBHTTP/interface/bootstrap/js/bootstrap-popover.js
CodernityDBHTTP/interface/bootstrap/js/bootstrap-tooltip.js
CodernityDBHTTP/interface/bootstrap/js/bootstrap.js
CodernityDBHTTP/interface/bootstrap/js/bootstrap.min.js
CodernityDBHTTP/interface/images/logo.png
CodernityDBHTTP/interface/scripts/app.js
CodernityDBHTTP/interface/scripts/lib/jquery-1.7.2.min.js
CodernityDBHTTP/interface/scripts/lib/kk.js
CodernityDBHTTP/interface/scripts/lib/knockout-2.1.0.debug.js
CodernityDBHTTP/interface/scripts/lib/knockout-2.1.0.js
CodernityDBHTTP/interface/scripts/lib/notifier.js
CodernityDBHTTP/interface/scripts/lib/sammy.min.js
CodernityDBHTTP/interface/scripts/lib/codemirror/codemirror.css
CodernityDBHTTP/interface/scripts/lib/codemirror/codemirror.js
CodernityDBHTTP/interface/scripts/lib/codemirror/elegant.css
CodernityDBHTTP/interface/scripts/lib/codemirror/javascript.js
CodernityDBHTTP/interface/scripts/lib/codemirror/monokai.css
CodernityDBHTTP/interface/scripts/lib/codemirror/python.js
CodernityDB_HTTP.egg-info/PKG-INFO
CodernityDB_HTTP.egg-info/SOURCES.txt
CodernityDB_HTTP.egg-info/dependency_links.txt
CodernityDB_HTTP.egg-info/entry_points.txt
CodernityDB_HTTP.egg-info/requires.txt
CodernityDB_HTTP.egg-info/top_level.txt